darwin_ssl_sniffer/__init__.py
darwin_ssl_sniffer/__main__.py
darwin_ssl_sniffer/_version.py
darwin_ssl_sniffer/exceptions.py
darwin_ssl_sniffer/sniffer.py
darwin_ssl_sniffer/ssl_session.py
darwin_ssl_sniffer/syslog_parser.py
darwin_ssl_sniffer/tcp_simulation.py
darwin_ssl_sniffer-0.0.4.dist-info/METADATA
darwin_ssl_sniffer-0.0.4.dist-info/WHEEL
darwin_ssl_sniffer-0.0.4.dist-info/entry_points.txt
darwin_ssl_sniffer-0.0.4.dist-info/top_level.txt
darwin_ssl_sniffer-0.0.4.dist-info/RECORD
